.coveragerc
.pylintrc
.testr.conf
AUTHORS
ChangeLog
HACKING.rst
LICENSE
MANIFEST.in
README.rst
requirements.txt
setup.cfg
setup.py
test-requirements.txt
tox.ini
doc/source/conf.py
doc/source/index.rst
python_quantumclient.egg-info/PKG-INFO
python_quantumclient.egg-info/SOURCES.txt
python_quantumclient.egg-info/dependency_links.txt
python_quantumclient.egg-info/entry_points.txt
python_quantumclient.egg-info/not-zip-safe
python_quantumclient.egg-info/requires.txt
python_quantumclient.egg-info/top_level.txt
quantumclient/__init__.py
quantumclient/client.py
quantumclient/shell.py
quantumclient/version.py
quantumclient/common/__init__.py
quantumclient/common/exceptions.py
quantumclient/common/utils.py
quantumclient/quantum/__init__.py
quantumclient/quantum/v2_0/__init__.py
quantumclient/quantum/v2_0/port.py
quantumclient/v2_0/__init__.py
quantumclient/v2_0/client.py
tests/__init__.py
tools/quantum.bash_completion